hrflow/__init__.py
hrflow/__version__.py
hrflow/auth/__init__.py
hrflow/board/__init__.py
hrflow/core/__init__.py
hrflow/core/rate_limit.py
hrflow/core/validation.py
hrflow/hrflow.py
hrflow/job/__init__.py
hrflow/job/asking.py
hrflow/job/embedding.py
hrflow/job/matching.py
hrflow/job/parsing.py
hrflow/job/reasoning.py
hrflow/job/scoring.py
hrflow/job/searching.py
hrflow/job/storing.py
hrflow/profile/__init__.py
hrflow/profile/asking.py
hrflow/profile/attachment.py
hrflow/profile/embedding.py
hrflow/profile/grading.py
hrflow/profile/matching.py
hrflow/profile/parsing.py
hrflow/profile/reasoning.py
hrflow/profile/revealing.py
hrflow/profile/scoring.py
hrflow/profile/searching.py
hrflow/profile/storing.py
hrflow/profile/unfolding.py
hrflow/rating/__init__.py
hrflow/schemas.py
hrflow/source/__init__.py
hrflow/text/__init__.py
hrflow/text/embedding.py
hrflow/text/imaging.py
hrflow/text/linking.py
hrflow/text/ocr.py
hrflow/text/parsing.py
hrflow/text/tagging.py
hrflow/tracking/__init__.py
hrflow/utils/__init__.py
hrflow/utils/evaluation/__init__.py
hrflow/utils/evaluation/job.py
hrflow/utils/evaluation/profile.py
hrflow/utils/scoring.py
hrflow/utils/searching.py
hrflow/utils/storing.py
hrflow/webhook/__init__.py
hrflow/webhook/base64Wrapper.py
hrflow/webhook/bytesutils.py
hrflow/webhook/hmacutils.py
hrflow-4.2.0.dist-info/LICENSE.txt
hrflow-4.2.0.dist-info/METADATA
hrflow-4.2.0.dist-info/WHEEL
hrflow-4.2.0.dist-info/RECORD
