Metadata-Version: 2.1
Name: hrflow
Version: 4.2.0
Summary: Python hrflow.ai API package
Home-page: https://github.com/hrflow/python-hrflow-api
License: MIT
Author: HrFlow.ai
Author-email: contact@hrflow.ai
Requires-Python: >=3.8.1,<4.0.0
Classifier: License :: OSI Approved :: MIT License
Classifier: Programming Language :: Python :: 3
Classifier: Programming Language :: Python :: 3.9
Classifier: Programming Language :: Python :: 3.10
Classifier: Programming Language :: Python :: 3.11
Classifier: Programming Language :: Python :: 3.12
Requires-Dist: openpyxl (>=3.1.2,<4.0.0)
Requires-Dist: pydantic (>=1.10.8,<2.0.0)
Requires-Dist: requests (>=2.31.0,<3.0.0)
Requires-Dist: tqdm (>=4.66.2,<5.0.0)
Project-URL: Changelog, https://github.com/Riminder/python-hrflow-api/releases
Project-URL: Documentation, https://github.com/hrflow/python-hrflow-api
Project-URL: HrFlow.ai Documentation, https://developers.hrflow.ai
Project-URL: Repository, https://github.com/hrflow/python-hrflow-api
